LICENSE
MANIFEST.in
README.md
setup.py
django_highlight_here.egg-info/PKG-INFO
django_highlight_here.egg-info/SOURCES.txt
django_highlight_here.egg-info/dependency_links.txt
django_highlight_here.egg-info/requires.txt
django_highlight_here.egg-info/top_level.txt
highlight_here/__init__.py
highlight_here/templatetags/__init__.py
highlight_here/templatetags/highlight_here.py