Metadata-Version: 1.1
Name: django-highlight-here
Version: 0.0.1
Summary: Templatetags to add 'here' classes to appropriate elements.
Home-page: https://github.com/fusionbox/django-highlight-here
Author: Fusionbox programmers
Author-email: programmers@fusionbox.com
License: BSD
Keywords: django
Platform: any
Classifier: Environment :: Web Environment
Classifier: Framework :: Django
Requires: beautifulsoup4
